hydra_program/__init__.py
hydra_program/cli/__init__.py
hydra_program/cli/hpinit.py
hydra_program/cli/hprun.py
hydra_program/config_templates/hprun.yaml
hydra_program/config_templates/hydra/default.yaml
hydra_program/config_templates/hydra/help/hprun.yaml
hydra_program/config_templates/hydra/job_logging/rich_logging.yaml
hydra_program/config_templates/path/default.yaml
hydra_program/core/__init__.py
hydra_program/core/serialization.py
hydra_program/core/utils.py
hydra_program-0.1.1.dist-info/licenses/LICENSE
hydra_program-0.1.1.dist-info/METADATA
hydra_program-0.1.1.dist-info/WHEEL
hydra_program-0.1.1.dist-info/entry_points.txt
hydra_program-0.1.1.dist-info/top_level.txt
hydra_program-0.1.1.dist-info/RECORD
