Metadata-Version: 2.4
Name: hydra-program
Version: 0.1.1
Summary: A hydra-based program running framework.
Author-email: Anke Tang <tang.anke@foxmail.com>
Project-URL: Repository, https://github.com/tanganke/hydra-program
Project-URL: Homepage, https://github.com/tanganke/hydra-program
Project-URL: Issues, https://github.com/tanganke/hydra-program/issues
Requires-Python: >=3.9
License-File: LICENSE
Requires-Dist: hydra-core
Requires-Dist: rich
Requires-Dist: bidict
Provides-Extra: dev
Requires-Dist: pytest; extra == "dev"
Requires-Dist: pytest-cov; extra == "dev"
Requires-Dist: black; extra == "dev"
Requires-Dist: isort; extra == "dev"
Requires-Dist: flake8; extra == "dev"
Requires-Dist: mypy; extra == "dev"
Provides-Extra: docs
Requires-Dist: sphinx; extra == "docs"
Requires-Dist: sphinx_rtd_theme; extra == "docs"
Requires-Dist: sphinx-autodoc-typehints; extra == "docs"
Requires-Dist: myst-parser; extra == "docs"
Requires-Dist: sphinx-autobuild; extra == "docs"
Dynamic: license-file
